MANIFEST.in
README.rst
setup.py
src/sentry_webhooks/__init__.py
src/sentry_webhooks/models.py
src/sentry_webhooks/plugin.py
src/sentry_webhooks.egg-info/PKG-INFO
src/sentry_webhooks.egg-info/SOURCES.txt
src/sentry_webhooks.egg-info/dependency_links.txt
src/sentry_webhooks.egg-info/entry_points.txt
src/sentry_webhooks.egg-info/not-zip-safe
src/sentry_webhooks.egg-info/top_level.txt