Metadata-Version: 1.1
Name: sentry-webhooks
Version: 0.3.1
Summary: A Sentry extension which integrates web hooks.
Home-page: http://github.com/getsentry/sentry-webhooks
Author: David Cramer
Author-email: dcramer@gmail.com
License: BSD
Platform: UNKNOWN
Classifier: Framework :: Django
Classifier: Intended Audience :: Developers
Classifier: Intended Audience :: System Administrators
Classifier: Operating System :: OS Independent
Classifier: Topic :: Software Development
